parlant/client/__init__.py
parlant/client/agents/__init__.py
parlant/client/agents/client.py
parlant/client/canned_responses/__init__.py
parlant/client/canned_responses/client.py
parlant/client/capabilities/__init__.py
parlant/client/capabilities/client.py
parlant/client/client.py
parlant/client/context_variables/__init__.py
parlant/client/context_variables/client.py
parlant/client/core/__init__.py
parlant/client/core/api_error.py
parlant/client/core/client_wrapper.py
parlant/client/core/datetime_utils.py
parlant/client/core/file.py
parlant/client/core/http_client.py
parlant/client/core/jsonable_encoder.py
parlant/client/core/pydantic_utilities.py
parlant/client/core/query_encoder.py
parlant/client/core/remove_none_from_dict.py
parlant/client/core/request_options.py
parlant/client/core/serialization.py
parlant/client/customers/__init__.py
parlant/client/customers/client.py
parlant/client/customers/types/__init__.py
parlant/client/customers/types/customers_list_response.py
parlant/client/errors/__init__.py
parlant/client/errors/gateway_timeout_error.py
parlant/client/errors/not_found_error.py
parlant/client/errors/service_unavailable_error.py
parlant/client/errors/unprocessable_entity_error.py
parlant/client/evaluations/__init__.py
parlant/client/evaluations/client.py
parlant/client/glossary/__init__.py
parlant/client/glossary/client.py
parlant/client/guidelines/__init__.py
parlant/client/guidelines/client.py
parlant/client/journeys/__init__.py
parlant/client/journeys/client.py
parlant/client/py.typed
parlant/client/relationships/__init__.py
parlant/client/relationships/client.py
parlant/client/services/__init__.py
parlant/client/services/client.py
parlant/client/sessions/__init__.py
parlant/client/sessions/client.py
parlant/client/sessions/types/__init__.py
parlant/client/sessions/types/sessions_list_response.py
parlant/client/tags/__init__.py
parlant/client/tags/client.py
parlant/client/types/__init__.py
parlant/client/types/agent.py
parlant_client-3.1.0.dist-info/METADATA
parlant_client-3.1.0.dist-info/WHEEL
parlant_client-3.1.0.dist-info/licenses/LICENSE
parlant_client-3.1.0.dist-info/RECORD
